[
  {
    "id": "comment_001",
    "text": "Honestly this update made the app unusable."
  },
  {
    "id": "comment_002",
    "text": "Great job developers! Everything works flawlessly now."
  },
  {
    "id": "comment_003",
    "text": "It's okay, nothing groundbreaking."
  },
  {
    "id": "comment_004",
    "text": "Wow. Another bug. I\u2019m shocked."
  },
  {
    "id": "comment_005",
    "text": "I can't believe they actually fixed it!"
  },
  {
    "id": "comment_006",
    "text": "This is garbage, just like the last version."
  },
  {
    "id": "comment_007",
    "text": "Much smoother now, thank you!"
  },
  {
    "id": "comment_008",
    "text": "Who thought this layout was a good idea?"
  },
  {
    "id": "comment_009",
    "text": "Everything's broken... again."
  },
  {
    "id": "comment_010",
    "text": "It's running faster, and I love the new features."
  },
  {
    "id": "comment_011",
    "text": "Not the worst update, but far from good."
  },
  {
    "id": "comment_012",
    "text": "I laughed out loud when I saw what they changed. Impressive."
  },
  {
    "id": "comment_013",
    "text": "I don\u2019t care anymore. Let them ruin it."
  },
  {
    "id": "comment_014",
    "text": "So clean and responsive, great UX!"
  },
  {
    "id": "comment_015",
    "text": "As expected. They didn\u2019t listen to feedback."
  },
  {
    "id": "comment_016",
    "text": "Still crashes. What a surprise."
  },
  {
    "id": "comment_017",
    "text": "Absolutely nailed it. Well done!"
  },
  {
    "id": "comment_018",
    "text": "Functional but ugly."
  },
  {
    "id": "comment_019",
    "text": "All this hype for what? It's the same thing."
  },
  {
    "id": "comment_020",
    "text": "At least it's not worse."
  },
  {
    "id": "comment_021",
    "text": "Solid improvement over the last version."
  },
  {
    "id": "comment_022",
    "text": "Worse than ever. Impressive regression."
  },
  {
    "id": "comment_023",
    "text": "No opinion really. It\u2019s just... there."
  },
  {
    "id": "comment_024",
    "text": "Everything loads instantly now, fantastic work."
  },
  {
    "id": "comment_025",
    "text": "Yeah, because changing the icon totally fixed the real issues."
  },
  {
    "id": "comment_026",
    "text": "This is why we can\u2019t have nice things."
  },
  {
    "id": "comment_027",
    "text": "Finally! A feature I\u2019ve been begging for."
  },
  {
    "id": "comment_028",
    "text": "It doesn\u2019t crash anymore. Is this heaven?"
  },
  {
    "id": "comment_029",
    "text": "Still bloated. Still awful."
  },
  {
    "id": "comment_030",
    "text": "Meh. It\u2019s serviceable."
  },
  {
    "id": "comment_031",
    "text": "Literally unusable on Android now."
  },
  {
    "id": "comment_032",
    "text": "The redesign is beautiful and sleek."
  },
  {
    "id": "comment_033",
    "text": "Great! Now my phone heats up after 3 minutes!"
  },
  {
    "id": "comment_034",
    "text": "Can we just go back to the version that worked?"
  },
  {
    "id": "comment_035",
    "text": "Bold move. I kinda like it."
  },
  {
    "id": "comment_036",
    "text": "The fact that this works is a miracle."
  },
  {
    "id": "comment_037",
    "text": "They listened to user feedback for once."
  },
  {
    "id": "comment_038",
    "text": "Took them long enough to fix a basic issue."
  },
  {
    "id": "comment_039",
    "text": "Smooth animations, intuitive flow, A++"
  },
  {
    "id": "comment_040",
    "text": "Wow, such innovation. A new shade of blue."
  },
  {
    "id": "comment_041",
    "text": "Neutral on this. Could go either way."
  },
  {
    "id": "comment_042",
    "text": "So proud of this dev team!"
  },
  {
    "id": "comment_043",
    "text": "Uninstalling. I've had enough."
  },
  {
    "id": "comment_044",
    "text": "The transition was buttery smooth."
  },
  {
    "id": "comment_045",
    "text": "It\u2019s still better than what Facebook does."
  },
  {
    "id": "comment_046",
    "text": "I expected disappointment and got it."
  },
  {
    "id": "comment_047",
    "text": "Flawless. Just flawless."
  },
  {
    "id": "comment_048",
    "text": "Kind of a joke now."
  },
  {
    "id": "comment_049",
    "text": "Performance is stable, and UI is tidy."
  },
  {
    "id": "comment_050",
    "text": "Brilliant. They broke the only part that worked."
  }
]